acclimatise/__init__.py
acclimatise/cli.py
acclimatise/cli_types.py
acclimatise/model.py
acclimatise/name_generation.py
acclimatise/nlp.py
acclimatise/parser.py
acclimatise/yaml.py
acclimatise/converter/__init__.py
acclimatise/converter/cwl.py
acclimatise/converter/wdl.py
acclimatise/converter/yml.py
acclimatise/execution/__init__.py
acclimatise/execution/docker.py
acclimatise/execution/local.py
acclimatise/flag_parser/__init__.py
acclimatise/flag_parser/elements.py
acclimatise/flag_parser/parser.py
acclimatise/usage_parser/__init__.py
acclimatise/usage_parser/elements.py
acclimatise/usage_parser/model.py
acclimatise/usage_parser/parser.py
test/__init__.py
test/conftest.py
test/test_cli.py
test/test_convert.py
test/test_explore_e2e.py
test/test_parse_e2e.py
test/test_type_inference.py
test/test_yaml_dump.py
test/util.py
test/executors/__init__.py
test/executors/test_docker.py
test/executors/test_local.py
test/name_generation/__init__.py
test/name_generation/conftest.py
test/name_generation/test_batch.py
test/name_generation/test_case.py
test/name_generation/test_description.py
test/name_generation/test_group.py
test/name_generation/test_single_flag.py
acclimatise-1.2.0.dist-info/LICENSE
acclimatise-1.2.0.dist-info/METADATA
acclimatise-1.2.0.dist-info/WHEEL
acclimatise-1.2.0.dist-info/entry_points.txt
acclimatise-1.2.0.dist-info/top_level.txt
acclimatise-1.2.0.dist-info/RECORD
